sprockets_dynamodb/__init__.py
sprockets_dynamodb/client.py
sprockets_dynamodb/exceptions.py
sprockets_dynamodb/mixin.py
sprockets_dynamodb/utils.py
sprockets_dynamodb-3.1.0.dist-info/LICENSE
sprockets_dynamodb-3.1.0.dist-info/METADATA
sprockets_dynamodb-3.1.0.dist-info/WHEEL
sprockets_dynamodb-3.1.0.dist-info/top_level.txt
sprockets_dynamodb-3.1.0.dist-info/zip-safe
sprockets_dynamodb-3.1.0.dist-info/RECORD
